astroplotlib-0.2.6.data/scripts/calculate_sky.py
astroplotlib-0.2.6.data/scripts/calibration.py
astroplotlib-0.2.6.data/scripts/elme_images.py
astroplotlib-0.2.6.data/scripts/guicata.py
astroplotlib-0.2.6.data/scripts/guiellipse.py
astroplotlib-0.2.6.data/scripts/guiregions.py
astroplotlib-0.2.6.data/scripts/mag.sh
astroplotlib-0.2.6.data/scripts/slit.py
cata/__init__.py
plot_ellipse/__init__.py
plot_functions/__init__.py
plot_slit/__init__.py
sky/__init__.py
astroplotlib-0.2.6.dist-info/LICENSE.txt
astroplotlib-0.2.6.dist-info/METADATA
astroplotlib-0.2.6.dist-info/WHEEL
astroplotlib-0.2.6.dist-info/top_level.txt
astroplotlib-0.2.6.dist-info/RECORD
