Metadata-Version: 2.1
Name: astroplotlib
Version: 0.2.6
Summary: Python scripts to handle astronomical images
Home-page: https://gitlab.com/joseaher/astrocubelib
Author: J. A. Hernandez-Jimenez
Author-email: joseaher@gmail.com
License-File: LICENSE.txt
